{
  "clauses": [
    {
      "id": "pancreator.contract_runner_rego.package_shape",
      "path": "/lib/memory/features/platform-substrate/pancreator-contract-runner-rego/contracts/pancreator.contract_runner_rego.package_shape.yaml",
      "owner": "contract-writer",
      "appliesTo": {
        "kind": "file-path",
        "glob": "lib/internal/packages/@pancreator/contract-runner-rego/**"
      }
    },
    {
      "id": "pancreator.contract_runner_rego.readme_ergonomics",
      "path": "/lib/memory/features/platform-substrate/pancreator-contract-runner-rego/contracts/pancreator.contract_runner_rego.readme_ergonomics.yaml",
      "owner": "contract-writer",
      "appliesTo": {
        "kind": "artifact-symbol",
        "path": "lib/internal/packages/@pancreator/contract-runner-rego/README.md",
        "symbol": "# Quickstart",
        "contentHash": "15dc4f7"
      }
    }
  ]
}
